astha_client/__init__.py
astha_client/client.py
astha_client/config.py
astha_client/exceptions.py
astha_client/policy.py
astha_client/py.typed
astha_client/types.py
astha_client/_internal/__init__.py
astha_client/_internal/async_utils.py
astha_client-0.1.2.dist-info/METADATA
astha_client-0.1.2.dist-info/WHEEL
astha_client-0.1.2.dist-info/RECORD
