Metadata-Version: 2.4
Name: astha-client
Version: 0.1.2
Summary: Python SDK for Astha AI platform
License: MIT
Keywords: agents,ai,astha,langchain,mcp,oidc,orchestration,rbac,sdk
Classifier: Development Status :: 3 - Alpha
Classifier: Intended Audience :: Developers
Classifier: License :: OSI Approved :: MIT License
Classifier: Programming Language :: Python :: 3
Classifier: Programming Language :: Python :: 3.11
Classifier: Programming Language :: Python :: 3.12
Classifier: Programming Language :: Python :: 3.13
Classifier: Topic :: Software Development :: Libraries :: Python Modules
Requires-Python: >=3.11
Requires-Dist: httpx>=0.27.0
Requires-Dist: langchain-anthropic>=1.3.0
Requires-Dist: mcp-use>=1.5.1
Requires-Dist: mcp>=0.9.0
Requires-Dist: python-dotenv>=1.2.1
Provides-Extra: dev
Requires-Dist: black>=23.0.0; extra == 'dev'
Requires-Dist: build>=1.0.0; extra == 'dev'
Requires-Dist: mypy>=1.0.0; extra == 'dev'
Requires-Dist: pytest-asyncio>=0.21.0; extra == 'dev'
Requires-Dist: pytest>=7.0.0; extra == 'dev'
Requires-Dist: ruff>=0.1.0; extra == 'dev'
Requires-Dist: twine>=5.0.0; extra == 'dev'
Provides-Extra: jupyter
Requires-Dist: nest-asyncio>=1.5.0; extra == 'jupyter'
